gcloud/aio/datastore/__init__.py
gcloud/aio/datastore/array.py
gcloud/aio/datastore/constants.py
gcloud/aio/datastore/datastore.py
gcloud/aio/datastore/datastore_operation.py
gcloud/aio/datastore/entity.py
gcloud/aio/datastore/filter.py
gcloud/aio/datastore/key.py
gcloud/aio/datastore/lat_lng.py
gcloud/aio/datastore/mutation.py
gcloud/aio/datastore/projection.py
gcloud/aio/datastore/property_order.py
gcloud/aio/datastore/py.typed
gcloud/aio/datastore/query.py
gcloud/aio/datastore/query_explain.py
gcloud/aio/datastore/transaction_options.py
gcloud/aio/datastore/value.py
gcloud/aio/py.typed
gcloud/py.typed
gcloud_aio_datastore-9.1.0.dist-info/LICENSE
gcloud_aio_datastore-9.1.0.dist-info/METADATA
gcloud_aio_datastore-9.1.0.dist-info/WHEEL
gcloud_aio_datastore-9.1.0.dist-info/RECORD
