Metadata-Version: 2.3
Name: gcloud-aio-datastore
Version: 9.1.0
Summary: Python Client for Google Cloud Datastore
License: MIT
Author: Vi Engineering
Author-email: voiceai-eng@dialpad.com
Requires-Python: >=3.9,<4.0
Classifier: Development Status :: 5 - Production/Stable
Classifier: Intended Audience :: Developers
Classifier: License :: OSI Approved :: MIT License
Classifier: Operating System :: OS Independent
Classifier: Programming Language :: Python :: 3
Classifier: Programming Language :: Python :: 3.9
Classifier: Programming Language :: Python :: 3.10
Classifier: Programming Language :: Python :: 3.11
Classifier: Programming Language :: Python :: 3.12
Classifier: Programming Language :: Python :: 3.13
Classifier: Topic :: Internet
Requires-Dist: gcloud-aio-auth (>=3.1.0,<6.0.0)
Project-URL: Repository, https://github.com/talkiq/gcloud-aio
